textoutpc/__init__.py
textoutpc/builtin/__init__.py
textoutpc/builtin/nodes.py
textoutpc/builtin/parsers.py
textoutpc/errors.py
textoutpc/frontend.py
textoutpc/lexer.py
textoutpc/misc.py
textoutpc/nodes.py
textoutpc/parser.py
textoutpc/py.typed
textoutpc/tags.py
textoutpc-0.3.dist-info/LICENSE.txt
textoutpc-0.3.dist-info/METADATA
textoutpc-0.3.dist-info/WHEEL
textoutpc-0.3.dist-info/RECORD
