Metadata-Version: 2.3
Name: textoutpc
Version: 0.3
Summary: BBCode parser and renderer for Planète Casio
Keywords: planète casio,textout,bbcode,translator,parser
Author: Thomas Touhey
Author-email: thomas@touhey.fr
Requires-Python: >=3.9,<4.0
Classifier: Development Status :: 2 - Pre-Alpha
Classifier: License :: OSI Approved :: CEA CNRS Inria Logiciel Libre License, version 2.1 (CeCILL-2.1)
Classifier: Natural Language :: French
Classifier: Operating System :: OS Independent
Classifier: Programming Language :: Python :: 3
Classifier: Intended Audience :: Developers
Classifier: Topic :: Internet :: WWW/HTTP :: Dynamic Content :: CGI Tools/Libraries
Classifier: Topic :: Text Processing :: Markup :: HTML
Requires-Dist: docutils (>=0.20,<0.21)
Requires-Dist: eval-type-backport (>=0.2,<0.3) ; python_version < "3.10"
Requires-Dist: pydantic (>=2.9,<3)
Requires-Dist: regex (>=2024.11.6)
Requires-Dist: thcolor (>=0.4,<0.5)
Requires-Dist: typing-extensions (>=4.8,<5)
Project-URL: Bug Tracker, https://gitlab.com/thomas.touhey/textoutpc/-/issues
Project-URL: Documentation, https://textoutpc.touhey.pro/
Project-URL: Homepage, https://textoutpc.touhey.pro/
Project-URL: Source Code, https://gitlab.com/thomas.touhey/textoutpc
